ethernal/__init__.py
ethernal/backend/__init__.py
ethernal/backend/main.py
ethernal/backend/api/__init__.py
ethernal/backend/api/routes.py
ethernal/backend/config/__init__.py
ethernal/backend/config/settings.py
ethernal/backend/core/__init__.py
ethernal/backend/core/ai_engine.py
ethernal/backend/core/blockchain.py
ethernal/backend/core/prompt_manager.py
ethernal/backend/models/__init__.py
ethernal/backend/models/agent.py
ethernal/backend/models/token.py
ethernal/backend/services/__init__.py
ethernal/backend/services/agent_service.py
ethernal/backend/services/auth_service.py
ethernal/backend/services/deployment_service.py
ethernal/tests/__init__.py
ethernal-0.1.0.dist-info/METADATA
ethernal-0.1.0.dist-info/WHEEL
ethernal-0.1.0.dist-info/top_level.txt
ethernal-0.1.0.dist-info/RECORD
