Metadata-Version: 2.1
Name: ethernal
Version: 0.1.0
Summary: Ethernal - Enterprise AI Agent Cloud Platform
Home-page: https://github.com/ethernalcloud/ethernal
Author: ethernal
Author-email: ethernal@github.com
Classifier: Programming Language :: Python :: 3
Classifier: Framework :: FastAPI
Classifier: License :: OSI Approved :: MIT License
Classifier: Operating System :: OS Independent
Requires-Python: >=3.1
Requires-Dist: fastapi
Requires-Dist: uvicorn
Requires-Dist: pydantic
Requires-Dist: motor
Requires-Dist: solana
Requires-Dist: solders
Requires-Dist: openai
Requires-Dist: docker
Requires-Dist: kubernetes
Requires-Dist: passlib
Requires-Dist: PyJWT
